hgui.cpython-313-darwin.so
include/AL/al.h
include/AL/alc.h
include/AL/alext.h
include/AL/efx-creative.h
include/AL/efx-presets.h
include/AL/efx.h
include/GLFW/glfw3.h
include/GLFW/glfw3native.h
include/freetype2/freetype/config/ftconfig.h
include/freetype2/freetype/config/ftheader.h
include/freetype2/freetype/config/ftmodule.h
include/freetype2/freetype/config/ftoption.h
include/freetype2/freetype/config/ftstdlib.h
include/freetype2/freetype/config/integer-types.h
include/freetype2/freetype/config/mac-support.h
include/freetype2/freetype/config/public-macros.h
include/freetype2/freetype/freetype.h
include/freetype2/freetype/ftadvanc.h
include/freetype2/freetype/ftbbox.h
include/freetype2/freetype/ftbdf.h
include/freetype2/freetype/ftbitmap.h
include/freetype2/freetype/ftbzip2.h
include/freetype2/freetype/ftcache.h
include/freetype2/freetype/ftchapters.h
include/freetype2/freetype/ftcid.h
include/freetype2/freetype/ftcolor.h
include/freetype2/freetype/ftdriver.h
include/freetype2/freetype/fterrdef.h
include/freetype2/freetype/fterrors.h
include/freetype2/freetype/ftfntfmt.h
include/freetype2/freetype/ftgasp.h
include/freetype2/freetype/ftglyph.h
include/freetype2/freetype/ftgxval.h
include/freetype2/freetype/ftgzip.h
include/freetype2/freetype/ftimage.h
include/freetype2/freetype/ftincrem.h
include/freetype2/freetype/ftlcdfil.h
include/freetype2/freetype/ftlist.h
include/freetype2/freetype/ftlogging.h
include/freetype2/freetype/ftlzw.h
include/freetype2/freetype/ftmac.h
include/freetype2/freetype/ftmm.h
include/freetype2/freetype/ftmodapi.h
include/freetype2/freetype/ftmoderr.h
include/freetype2/freetype/ftotval.h
include/freetype2/freetype/ftoutln.h
include/freetype2/freetype/ftparams.h
include/freetype2/freetype/ftpfr.h
include/freetype2/freetype/ftrender.h
include/freetype2/freetype/ftsizes.h
include/freetype2/freetype/ftsnames.h
include/freetype2/freetype/ftstroke.h
include/freetype2/freetype/ftsynth.h
include/freetype2/freetype/ftsystem.h
hgui-4.0.4.dist-info/METADATA
hgui-4.0.4.dist-info/WHEEL
hgui-4.0.4.dist-info/licenses/LICENSE
hgui-4.0.4.dist-info/RECORD
