Metadata-Version: 2.2
Name: hgui
Version: 4.0.4
Summary: Python binding of HorizonGUI a graphical interface in c++ with OpenGl
Keywords: hgui,GUI Library,User Interface Library,Cross-platform GUI,HorizonGUI,Horizon UI Library,Graphical User Interface Library,UI Toolkit,Horizon GUI Framework,HorizonUI,Modern UI Library,Customizable UI Components,GUI Development Kit,GUI Design Framework,GUI Widgets,HorizonGUI Components,HorizonUI Toolkit,User Interface Components,Horizon GUI Controls,HorizonUI Elements,Responsive UI Library
Author: Horizon-NTH
Classifier: Programming Language :: C++
Classifier: License :: OSI Approved :: MIT License
Classifier: Development Status :: 5 - Production/Stable
Classifier: Operating System :: OS Independent
Classifier: Intended Audience :: Developers
Classifier: Natural Language :: English
Classifier: Topic :: Multimedia :: Graphics
Classifier: Topic :: Software Development :: Libraries
Project-URL: Homepage, https://github.com/Horizon-NTH/HorizonGUI
Project-URL: Repository, https://github.com/Horizon-NTH/HorizonGUI
Project-URL: Issues, https://github.com/Horizon-NTH/HorizonGUI/issues
Project-URL: Documentation, https://github.com/Horizon-NTH/HorizonGUI/wiki
Requires-Python: >=3.8
